monotrail-0.1.0.dist-info/METADATA
monotrail-0.1.0.dist-info/WHEEL
monotrail-0.1.0.dist-info/entry_points.txt
monotrail/_monotrail_finder.py
monotrail/run_script.py
monotrail/monotrail.pyi
monotrail/run_python.py
monotrail/__init__.py
monotrail/_load_monotrail.py
monotrail/monotrail.abi3.so
monotrail-0.1.0.dist-info/RECORD
