Metadata-Version: 2.1
Name: monotrail
Version: 0.1.0
Requires-Dist: importlib_metadata ; python_version < "3.7"
Summary: This proof of concept shows how to use python packages without virtualenvs
